RISC-V_Pipelined_Core/Instruction_Memory.sv
module Instruction_Memory(
    input logic rst,
    input logic [31:0] A,
    output logic [31:0] RD);

    logic [31:0] mem [1023:0];

    assign RD = (rst == 1'b0) ? {32{1'b0}} : mem[A[31:2]];

    initial begin
        $readmemh("memfile.hex", mem);
    end
    
endmodule

RISC-V_Pipelined_Core/PC_Adder.sv
module PC_Adder(
    input logic [31:0] a, b,
    output logic [31:0] c);

    assign c = a + b;

endmodule

RISC-V_Pipelined_Core/PC.sv
module PC_Module (
    // Inputs and Outputs
    input logic clk, rst,
    input logic [31:0] PC_Next,
    output logic [31:0] PC);

    always_ff @ (posedge clk) begin
        if (rst == 1'b0)
           PC <= {32{1'b0}};

        else
            PC <= PC_Next;
    end

endmodule

RISC-V_Pipelined_Core/Mux.sv
module Mux (
    input logic [31:0] a, b,
    input logic s,
    output logic [31:0] c);

    assign c = (~s) ? a : b;

endmodule

module Mux_3_by_1(
    input logic [31:0] a, b, c,
    input logic [1:0] s,
    output logic [31:0] d);

    assign d = (s == 2'b00) ? a : (s == 2'b01) ? b : (s == 2'b10) ? c : 32'h00000000; 

endmodule

RISC-V_Pipelined_Core/Fetch_Cycle.sv
module fetch_cycle(
    // Inputs and outputs
    input logic clk, rst, PCSrcE, 
    input logic [31:0] PCTargetE,
    output logic [31:0] InstrD, PCD, PCPlus4D);

    // Declaration of internal logic
    logic [31:0] PC_F, PCF, PCPlus4F, InstrF;

    // Declaration of register
    logic [31:0] InstrF_reg, PCF_reg, PCPlus4F_reg;

    // Initiating Modules

    // Declare PC Mux
    Mux PC_Mux(
        .a(PCPlus4F), 
        .b(PCTargetE), 
        .s(PCSrcE),
        .c(PC_F));

    // Declare Program Counter
    PC_Module Program_Counter(
        .clk(clk),
        .rst(rst),
        .PC_Next(PC_F),
        .PC(PCF));

    // Declare PC Adder
    PC_Adder PC_Adder(
        .a(PCF),
        .b(32'h00000004),
        .c(PCPlus4F));

    // Declare Instruction Memory
    Instruction_Memory IMEM(
        .rst(rst),
        .A(PCF),
        .RD(InstrF));

    // Fetch Cycle Register Logic
    always_ff @(posedge clk or negedge rst) begin
        if (rst == 1'b0) begin
            InstrF_reg <= 32'h00000000;
            PCF_reg <= 32'h00000000;
            PCPlus4F_reg <= 32'h00000000;
        end 
        
        else begin
            InstrF_reg <= InstrF;
            PCF_reg <= PCF;
            PCPlus4F_reg <= PCPlus4F;
        end

    end

    // Assigning Registers Value to the Output port
    assign InstrD = (rst == 1'b0) ? 32'h00000000 : InstrF_reg;
    assign PCD = (rst == 1'b0) ? 32'h00000000 : PCF_reg;
    assign PCPlus4D = (rst == 1'b0) ? 32'h00000000 : PCPlus4F_reg;

endmodule

RISC-V_Pipelined_Core/fetch_cycle_tb.sv
`include "fetch_cycle.sv"
module fetch_cycle_tb();

    logic clk = 0, rst, PCSrcE;
    logic [31:0] PCTargetE;
    wire [31:0] InstrD, PCD, PCPlus4D;
    
    // Declare the design under test
    fetch_cycle dut (
                    .clk(clk), 
                    .rst(rst), 
                    .PCSrcE(PCSrcE),
                    .PCTargetE(PCTargetE),
                    .InstrD(InstrD), 
                    .PCD(PCD), 
                    .PCPlus4D(PCPlus4D));


    // Generation of clock
    always begin
        clk = ~clk;
        #50;
    end

    // Provide the stimulus
    initial begin
        rst <= 1'b0;
        #200
        rst <= 1'b1;
        PCSrcE <= 1'b0;
        PCTargetE <= 32'h00000000;
        #500
        $finish;



    end

    // Generation of vcd
    initial begin 
        $dumpfile("fetch_cycle_tb.vcd");
        $dumpvars(0, fetch_cycle_tb);
    end

endmodule

RISC-V_Pipelined_Core/fetch_cycle_tb.vcd
$date
	Wed Jul 10 12:49:34 2024
$end
$version
	Icarus Verilog
$end
$timescale
	1s
$end
$scope module fetch_cycle_tb $end
$var wire 32 ! PCPlus4D [31:0] $end
$var wire 32 " PCD [31:0] $end
$var wire 32 # InstrD [31:0] $end
$var reg 1 $ PCSrcE $end
$var reg 32 % PCTargetE [31:0] $end
$var reg 1 & clk $end
$var reg 1 ' rst $end
$scope module dut $end
$var wire 1 $ PCSrcE $end
$var wire 32 ( PCTargetE [31:0] $end
$var wire 1 & clk $end
$var wire 1 ' rst $end
$var wire 32 ) PC_F [31:0] $end
$var wire 32 * PCPlus4F [31:0] $end
$var wire 32 + PCPlus4D [31:0] $end
$var wire 32 , PCF [31:0] $end
$var wire 32 - PCD [31:0] $end
$var wire 32 . InstrF [31:0] $end
$var wire 32 / InstrD [31:0] $end
$var reg 32 0 InstrF_reg [31:0] $end
$var reg 32 1 PCF_reg [31:0] $end
$var reg 32 2 PCPlus4F_reg [31:0] $end
$scope module IMEM $end
$var wire 1 ' rst $end
$var wire 32 3 RD [31:0] $end
$var wire 32 4 A [31:0] $end
$upscope $end
$scope module PC_Adder $end
$var wire 32 5 b [31:0] $end
$var wire 32 6 c [31:0] $end
$var wire 32 7 a [31:0] $end
$upscope $end
$scope module PC_Mux $end
$var wire 32 8 a [31:0] $end
$var wire 32 9 b [31:0] $end
$var wire 1 $ s $end
$var wire 32 : c [31:0] $end
$upscope $end
$scope module Program_Counter $end
$var wire 32 ; PC_Next [31:0] $end
$var wire 1 & clk $end
$var wire 1 ' rst $end
$var reg 32 < PC [31:0] $end
$upscope $end
$upscope $end
$upscope $end
$enddefinitions $end
$comment Show the parameter values. $end
$dumpall
$end
#0
$dumpvars
bx <
bx ;
bx :
bx 9
bx 8
bx 7
bx 6
b100 5
bx 4
b0 3
b0 2
b0 1
b0 0
b0 /
b0 .
b0 -
bx ,
b0 +
bx *
bx )
bx (
0'
1&
bx %
x$
b0 #
b0 "
b0 !
$end
#50
0&
#100
b100 *
b100 6
b100 8
b0 ,
b0 4
b0 7
b0 <
1&
#150
0&
#200
b10100000000001010010011 .
b10100000000001010010011 3
b100 )
b100 :
b100 ;
b0 %
b0 (
b0 9
0$
1'
1&
#250
0&
#300
b1100000000001100010011 .
b1100000000001100010011 3
b1000 )
b1000 :
b1000 ;
b100 !
b100 +
b10100000000001010010011 #
b10100000000001010010011 /
b1000 *
b1000 6
b1000 8
b100 ,
b100 4
b100 7
b100 <
b100 2
b10100000000001010010011 0
1&
#350
0&
#400
b11000101000001110110011 .
b11000101000001110110011 3
b1100 )
b1100 :
b1100 ;
b1000 !
b1000 +
b100 "
b100 -
b1100000000001100010011 #
b1100000000001100010011 /
b1100 *
b1100 6
b1100 8
b1000 ,
b1000 4
b1000 7
b1000 <
b1000 2
b100 1
b1100000000001100010011 0
1&
#450
0&
#500
b10010000000011 .
b10010000000011 3
b10000 )
b10000 :
b10000 ;
b1100 !
b1100 +
b1000 "
b1000 -
b11000101000001110110011 #
b11000101000001110110011 /
b10000 *
b10000 6
b10000 8
b1100 ,
b1100 4
b1100 7
b1100 <
b1100 2
b1000 1
b11000101000001110110011 0
1&
#550
0&
#600
b100000000010010010011 .
b100000000010010010011 3
b10100 )
b10100 :
b10100 ;
b10000 !
b10000 +
b1100 "
b1100 -
b10010000000011 #
b10010000000011 /
b10100 *
b10100 6
b10100 8
b10000 ,
b10000 4
b10000 7
b10000 <
b10000 2
b1100 1
b10010000000011 0
1&
#650
0&
#700
b100101000000010100110011 .
b100101000000010100110011 3
b11000 )
b11000 :
b11000 ;
b10100 !
b10100 +
b10000 "
b10000 -
b100000000010010010011 #
b100000000010010010011 /
b11000 *
b11000 6
b11000 8
b10100 ,
b10100 4
b10100 7
b10100 <
b10100 2
b10000 1
b100000000010010010011 0
1&
